nystromformer/__init__.py
nystromformer/nystrom_attention.py
nystromformer/nystromformer.py
nystromformer/test_nystrom_attention.py
nystromformer/test_nystromformer.py
nystromformer/utils.py
nystromformer/version.py
nystromformer-0.1.0.dist-info/LICENSE
nystromformer-0.1.0.dist-info/METADATA
nystromformer-0.1.0.dist-info/WHEEL
nystromformer-0.1.0.dist-info/top_level.txt
nystromformer-0.1.0.dist-info/RECORD
